copulabayesnet/__init__.py
copulabayesnet/bncopula.py
copulabayesnet/cop_plot.py
copulabayesnet/data_preprocessor.py
copulabayesnet/data_processor.py
copulabayesnet/spatial_tools.py
copulabayesnet-0.1.6.dist-info/LICENCE.txt
copulabayesnet-0.1.6.dist-info/METADATA
copulabayesnet-0.1.6.dist-info/WHEEL
copulabayesnet-0.1.6.dist-info/top_level.txt
copulabayesnet-0.1.6.dist-info/RECORD
